{"TDvVambMUqKbY8UkEGOerg==":"mbr.jpg","HaZotFCe/YbBGZnwSFed+Q==":"mbr-1920x1276.jpg","4Bla28QIU4TdZit5gyJ1lw==":"mbr-1920x1279.jpg","Qe3Ee923RDmhqo3ZTPcXxQ==":"main-1900x1267.jpg","JBR2mQeCBFHMtyAjneeX9A==":"main-photo-128x139.png","QTMX/IXrvbnI1qq+PvSv2A==":"convener-696x696.jpg","MQmLscTAU6cEplI5q0F3qQ==":"president-696x690.jpg","n4fiYKh09nhmeISaFY6wuA==":"vp-1-696x698.jpg","3q2D6FYMh/WUIvzlp5cj/Q==":"vp-2-696x696.jpg","WiAmrYfyspdaHdB16518Rg==":"gs-378x368.png","XTra5pJ4PUulOB+QXLsvSw==":"ts-509x606.jpg","5Rpeb1benPj+Et5NYuCAdw==":"tr-518x536.png","WfIBY2uuB5x92oeTxHax9g==":"tr-1-518x536.png","iH0EikxNVINep3yiTnrjKA==":"president-696x690.jpeg","aO+RQ+lQJQwQeBAt3/yGTw==":"vp-1-696x698.jpeg","6YuNze+Ret+xBZ7WRjprXw==":"vp-2-696x696.jpeg","M4SB7PuHqn1fEABewEO9lA==":"tr-2-518x536.png","T9ldFl0+iGLNgEw56gsZbg==":"gs-1-378x368.png","8ws655SAEPxyAsyhOieQtA==":"mps-696x696.jpeg","mfFZ8kK0qgjOOKVPwKqyhw==":"mbr-1920x1280.jpg","5seXprxA/RkNCtoPtkYd3g==":"mbr-1-1920x1280.jpg","UPgGNDuu8zqkpPQt5p/k+A==":"ts-509x606.jpeg","0mULw60Ma0RlnOmwA490MA==":"sds-696x767.jpg","TCL1ZUkw6purZZ297A0zNw==":"sds-696x767.jpeg","VmcFmqgRyEoojehP+TtapA==":"eds-696x726.jpeg","PP8fst+uAcWwuusq2PBfXg==":"gd-1-554x554.png","4dxKQd03gMpy2QGhaxLwHQ==":"gd-2-126x135.png","DV3m1j62BNveBoLBGNI0Kg==":"em-1-488x501.png","AwE4TPfVIxJANvEibrDIXA==":"gd-3-126x135.png","SmiSUanR+eVAmcK4bg06Aw==":"registrar-479x598.png","eOIhEfSzni/MnEU7wKlJ5g==":"head,%20department%20of%20computer%20science%20and%20engineering-554x554.jpeg","JpA1bj/517/5/JJR0ocKFQ==":"director%20of%20student%20affairs-365x347.png","ZIzSkKMFbl0GQSz5oRbiJw==":"kaushik%20sarker-219x201.png","lXTjyRXFBS4GxwX7eDXJeQ==":"convener-554x554.jpeg","Iq1JLlwLJLXUdTeo0v0o0w==":"em-2-554x551.png","b2dWtEh77spMoUeSYup/QQ==":"125223894_3464699443620068_8139662227916950212_o-1052x1052.png","ke5AALmuXO5rA1GR7DEXtg==":"evnt3-515x720.png","U7jF2809nN2i/vARp8DStQ==":"team-960x540.png","kiELa+EMw15Ti4s7Q+NiDQ==":"evnt2-696x444.jpg"}